pyams_utils/__init__.py
pyams_utils/adapter.py
pyams_utils/attr.py
pyams_utils/cache.py
pyams_utils/configure.zcml
pyams_utils/container.py
pyams_utils/context.py
pyams_utils/country.py
pyams_utils/data.py
pyams_utils/date.py
pyams_utils/decorator.py
pyams_utils/dict.py
pyams_utils/encoding.py
pyams_utils/factory.py
pyams_utils/fanstatic.py
pyams_utils/finder.py
pyams_utils/html.py
pyams_utils/i18n.py
pyams_utils/include.py
pyams_utils/inherit.py
pyams_utils/intids.py
pyams_utils/json.py
pyams_utils/list.py
pyams_utils/location.py
pyams_utils/lock.py
pyams_utils/monitor.py
pyams_utils/progress.py
pyams_utils/property.py
pyams_utils/pygments.py
pyams_utils/registry.py
pyams_utils/request.py
pyams_utils/rest.py
pyams_utils/rpc.py
pyams_utils/schema.py
pyams_utils/session.py
pyams_utils/size.py
pyams_utils/tales.py
pyams_utils/testing.py
pyams_utils/text.py
pyams_utils/transaction.py
pyams_utils/traversing.py
pyams_utils/unicode.py
pyams_utils/url.py
pyams_utils/vocabulary.py
pyams_utils/wsgi.py
pyams_utils/zodb.py
pyams_utils/doctests/README.rst
pyams_utils/doctests/adapter.rst
pyams_utils/doctests/attr.rst
pyams_utils/doctests/cache.rst
pyams_utils/doctests/container.rst
pyams_utils/doctests/context.rst
pyams_utils/doctests/data.rst
pyams_utils/doctests/date.rst
pyams_utils/doctests/factory.rst
pyams_utils/doctests/fanstatic.rst
pyams_utils/doctests/i18n.rst
pyams_utils/doctests/inherit.rst
pyams_utils/doctests/intids.rst
pyams_utils/doctests/list.rst
pyams_utils/doctests/location.rst
pyams_utils/doctests/lock.rst
pyams_utils/doctests/monitor.rst
pyams_utils/doctests/progress.rst
pyams_utils/doctests/property.rst
pyams_utils/doctests/protocol-http.rst
pyams_utils/doctests/protocol-socket.rst
pyams_utils/doctests/protocol-xmlrpc.rst
pyams_utils/doctests/pygments.rst
pyams_utils/doctests/registry.rst
pyams_utils/doctests/request.rst
pyams_utils/doctests/rest.rst
pyams_utils/doctests/rpc.rst
pyams_utils/doctests/schema.rst
pyams_utils/doctests/session.rst
pyams_utils-2.8.2.dist-info/LICENSE
pyams_utils-2.8.2.dist-info/METADATA
pyams_utils-2.8.2.dist-info/WHEEL
pyams_utils-2.8.2.dist-info/namespace_packages.txt
pyams_utils-2.8.2.dist-info/top_level.txt
pyams_utils-2.8.2.dist-info/RECORD
