Metadata-Version: 2.1
Name: pyams-utils
Version: 2.8.2
Summary: PyAMS generic modules
Home-page: https://pyams.readthedocs.io
Author: Thierry Florac
Author-email: tflorac@ulthar.net
License: ZPL
Keywords: Pyramid PyAMS
Classifier: License :: OSI Approved :: Zope Public License
Classifier: Development Status :: 4 - Beta
Classifier: Programming Language :: Python
Classifier: Framework :: Pyramid
Classifier: Topic :: Software Development :: Libraries :: Python Modules
Requires-Python: >=3.7
License-File: LICENSE
Requires-Dist: setuptools
Requires-Dist: ZEO
Requires-Dist: ZODB
Requires-Dist: babel
Requires-Dist: beaker
Requires-Dist: chameleon
Requires-Dist: colander
Requires-Dist: cornice
Requires-Dist: cornice-swagger
Requires-Dist: docutils
Requires-Dist: fanstatic
Requires-Dist: httplib2
Requires-Dist: lxml
Requires-Dist: markdown
Requires-Dist: persistent
Requires-Dist: pygments
Requires-Dist: pyramid >=2.0.0
Requires-Dist: pyramid-fanstatic
Requires-Dist: pyramid-rpc
Requires-Dist: pyramid-zodbconn
Requires-Dist: pytz
Requires-Dist: transaction
Requires-Dist: venusian
Requires-Dist: zope.annotation
Requires-Dist: zope.component
Requires-Dist: zope.container
Requires-Dist: zope.contentprovider
Requires-Dist: zope.copy
Requires-Dist: zope.dublincore
Requires-Dist: zope.interface
Requires-Dist: zope.intid
Requires-Dist: zope.keyreference
Requires-Dist: zope.lifecycleevent
Requires-Dist: zope.location
Requires-Dist: zope.schema
Requires-Dist: zope.traversing
Provides-Extra: test
Requires-Dist: pyramid-chameleon ; extra == 'test'
Requires-Dist: pyramid-zcml ; extra == 'test'
Requires-Dist: zope.site ; extra == 'test'
